<?xml version="1.0" encoding="UTF-8"?>

<databaseChangeLog xmlns="http://www.liquibase.org/xml/ns/dbchangelog/1.7"
	xmlns:xsi="http://www.w3.org/2001/XMLSchema-instance"
	xsi:schemaLocation="http://www.liquibase.org/xml/ns/dbchangelog/1.7
	http://www.liquibase.org/xml/ns/dbchangelog/dbchangelog-1.7.xsd">
	<preConditions>
		<or>
			<dbms type="oracle" />
			<dbms type="mysql" />
			<dbms type="postgresql" />
		</or>
	</preConditions>

	<changeSet author="uptdb45" id="1">
		<createTable tableName="CSM_PASSWORD_HISTORY">
			<column name="CSM_PASSWORD_HISTORY_ID" type="bigint(38)">
				<constraints nullable="false" primaryKey="true" />
			</column>
			<column name="LOGIN_NAME" type="varchar(100)">
				<constraints nullable="false" />
			</column>
			<column name="PASSWORD" type="varchar(255)">
				<constraints nullable="false" />
			</column>
		</createTable>

		<createTable tableName="CSM_CONFIGURATION_PROPERTIES">
			<column name="PROPERTY_KEY" type="varchar(300)">
				<constraints nullable="false" primaryKey="true" />
			</column>
			<column name="PROPERTY_VALUE" type="varchar(3000)">
			</column>
		</createTable>
	
		<addColumn tableName="CSM_USER">
			<column name="PASSWORD_EXPIRED" type="BOOL" defaultValue="0">
				<constraints nullable="false" />
			</column>
			<column name="PASSWORD_EXPIRY_DATE"  type="date">
				<constraints nullable="false" />
			</column>
			<column name="FIRST_TIME_LOGIN" type="BOOL" defaultValue="0">
				<constraints nullable="false" />
			</column>
			<column name="ACTIVE_FLAG" type="BOOL" defaultValue="1">
				<constraints nullable="false" />
			</column>
		</addColumn>
		<insert tableName="CSM_CONFIGURATION_PROPERTIES">
		    <column name="PROPERTY_KEY" valueNumeric="ALLOWED_ATTEMPTS"/>
		    <column name="PROPERTY_VALUE" value="3"/>
		</insert>
		<insert tableName="CSM_CONFIGURATION_PROPERTIES">
		    <column name="PROPERTY_KEY" valueNumeric="ALLOWED_LOGIN_TIME"/>
		    <column name="PROPERTY_VALUE" value="600000"/>
		</insert>
		<insert tableName="CSM_CONFIGURATION_PROPERTIES">
		    <column name="PROPERTY_KEY" valueNumeric="PASSWORD_EXPIRY_DAYS"/>
		    <column name="PROPERTY_VALUE" value="60"/>
		</insert>
		<insert tableName="CSM_CONFIGURATION_PROPERTIES">
		    <column name="PROPERTY_KEY" valueNumeric="PASSWORD_LOCKOUT_TIME"/>
		    <column name="PROPERTY_VALUE" value="1800000"/>
		</insert>
		<insert tableName="CSM_CONFIGURATION_PROPERTIES">
		    <column name="PROPERTY_KEY" valueNumeric="PASSWORD_MATCH_NUM"/>
		    <column name="PROPERTY_VALUE" value="24"/>
		</insert>
		<insert tableName="CSM_CONFIGURATION_PROPERTIES">
		    <column name="PROPERTY_KEY" valueNumeric="AES_ENCRYPTION_KEY"/>
		    <column name="PROPERTY_VALUE" value="super secret"/>
		</insert>
		<insert tableName="CSM_CONFIGURATION_PROPERTIES">
		    <column name="PROPERTY_KEY" valueNumeric="PASSWORD_PATTERN_MATCH"/>
		    <column name="PROPERTY_VALUE" value="(?=.*[A-Z])(?=.*\\d)(.{8,})$"/>
		</insert>		
	</changeSet>
</databaseChangeLog>