<?xml version="1.0" encoding="UTF-8"?>
 
<databaseChangeLog
	xmlns="http://www.liquibase.org/xml/ns/dbchangelog/1.7"
	xmlns:xsi="http://www.w3.org/2001/XMLSchema-instance"
	xsi:schemaLocation="http://www.liquibase.org/xml/ns/dbchangelog/1.7
	http://www.liquibase.org/xml/ns/dbchangelog/dbchangelog-1.7.xsd">
	<preConditions>            
		<or>
			<dbms type="oracle" />                     
			<dbms type="mysql" />                     
			<dbms type="postgresql" />                     
		</or>
	</preConditions>                        
	               	                                                       
   <changeSet author="uptdb42" id="1">

	 <createTable tableName="CSM_MAPPING">
		<column name="MAPPING_ID" type="bigint(20)">
			<constraints nullable="false" primaryKey="true" />
		</column>	
		<column name="APPLICATION_ID" type="BIGINT">
			<constraints nullable="false" />
		</column>
		<column name="OBJECT_NAME" type="varchar(4000)">
			<constraints nullable="false" />
		</column>
		<column name="ATTRIBUTE_NAME" type="varchar(100)">
			<constraints nullable="false" />
		</column>
		<column name="OBJECT_PACKAGE_NAME" type="varchar(100)">
			<constraints nullable="false" />
		</column>
		<column name="TABLE_NAME" type="varchar(100)" />
		<column name="TABLE_NAME_GROUP" type="varchar(100)" />
		<column name="TABLE_NAME_USER" type="varchar(100)" />
		<column name="VIEW_NAME_GROUP" type="varchar(100)" />
		<column name="VIEW_NAME_USER" type="varchar(100)" />
		<column name="ACTIVE_FLAG" type="tinyint" />
		<column name="MAINTAINED_FLAG" type="tinyint" />
		<column name="UPDATE_DATE" type="date" />			
      </createTable>

	<!--
      <addUniqueConstraint tableName="CSM_MAPPING"
			columnNames="OBJECT_NAME,ATTRIBUTE_NAME,APPLICATION_ID"
			constraintName="UQ_MP_OBJ_NAME_ATTRI_NAME_APP_ID" /> -->
    </changeSet>
</databaseChangeLog>

